adis/__init__.py
adis/adis.py
adis/adis_block.py
adis/adis_field_definition.py
adis/adis_file.py
adis/adis_lines.py
adis/adis_value.py
adis-1.0.1.dist-info/LICENSE
adis-1.0.1.dist-info/METADATA
adis-1.0.1.dist-info/WHEEL
adis-1.0.1.dist-info/top_level.txt
adis-1.0.1.dist-info/RECORD
