Metadata-Version: 2.1
Name: adis
Version: 1.0.1
Summary: A package for parsing ADIS files or creating new files in the ADIS format.
Home-page: https://github.com/smaxtec/adis
Author: smaXtec
Author-email: support@smaxtec.com
License: LGPLv3
Project-URL: Bug Tracker, https://github.com/smaxtec/adis/issues
Platform: UNKNOWN
Classifier: Programming Language :: Python :: 3
Classifier: License :: OSI Approved :: GNU Lesser General Public License v3 (LGPLv3)
Classifier: Operating System :: OS Independent
Requires-Python: >=3.8
License-File: LICENSE
